Project1/__init__.py
Project1/encryption.py
Project1/main.py
Project1/menu.py
StudentAndGradeManagementPackage-0.0.3.dist-info/LICENSE.txt
StudentAndGradeManagementPackage-0.0.3.dist-info/METADATA
StudentAndGradeManagementPackage-0.0.3.dist-info/WHEEL
StudentAndGradeManagementPackage-0.0.3.dist-info/top_level.txt
StudentAndGradeManagementPackage-0.0.3.dist-info/RECORD
